humanresources/__init__.py
humanresources/apps.py
humanresources/filters.py
humanresources/forms.py
humanresources/signals.py
humanresources/urls.py
humanresources/utils.py
humanresources/views.py
humanresources/apps/__init__.py
humanresources/apps/overview.py
humanresources/apps/contracts/__init__.py
humanresources/apps/contracts/contracts_create.py
humanresources/apps/contracts/contracts_form.py
humanresources/apps/contracts/contracts_list.py
humanresources/apps/contracts/contracts_view.py
humanresources/apps/contracts/payout_form.py
humanresources/apps/contracts/payout_list.py
humanresources/apps/dashboards/__init__.py
humanresources/apps/people/__init__.py
humanresources/apps/people/privateinfo.py
humanresources/apps/people/profile_privateinfo.py
humanresources/apps/proposals/__init__.py
humanresources/apps/proposals/proposal_view.py
humanresources/apps/proposals/proposals_create.py
humanresources/apps/proposals/proposals_form.py
humanresources/apps/proposals/proposals_list.py
humanresources/apps/reports/__init__.py
humanresources/apps/reports/contracts_per_year.py
humanresources/apps/reports/headcounts.py
humanresources/apps/reports/people_per_group.py
humanresources/apps/reports/people_per_year.py
humanresources/management/__init__.py
humanresources/management/commands/__init__.py
humanresources/management/commands/contracts_ending.py
humanresources/management/commands/contracts_with_payouts_ending.py
humanresources/management/commands/export_current_contract_status.py
humanresources/management/commands/import_budgets.py
humanresources/migrations/0001_initial.py
humanresources/migrations/__init__.py
humanresources/models/__init__.py
humanresources/models/fellowship_type.py
humanresources/models/id_document.py
humanresources/models/payment.py
humanresources/models/payout.py
humanresources/models/contract/__init__.py
humanresources/models/contract/contract.py
humanresources/models/contract/contract_file.py
humanresources/models/contract/contract_queryset.py
core_humanresources-0.7.dist-info/METADATA
core_humanresources-0.7.dist-info/WHEEL
core_humanresources-0.7.dist-info/top_level.txt
core_humanresources-0.7.dist-info/RECORD
