Metadata-Version: 2.1
Name: core-humanresources
Version: 0.7
Summary: Research CORE ERM - human resources module
Home-page: https://github.com/research-core/core-humanresources
Author: Ricardo Ribeiro, Hugo Cachitas
Author-email: ricardojvr@gmail.com, hugo.cachitas@research.fchampalimaud.org
License: MIT
Platform: UNKNOWN
Requires-Dist: django-localflavor
Requires-Dist: weasyprint
Requires-Dist: django-weasyprint
Requires-Dist: django-model-utils
Requires-Dist: django-money
Requires-Dist: core-common
Requires-Dist: core-people
Requires-Dist: core-finance
Requires-Dist: core-permissions
